mq4hemc/__init__.py
mq4hemc/_version.py
mq4hemc/hemc_observer.py
mq4hemc/hemc_queue.py
mq4hemc/hemc_service.py
mq4hemc/hemc_tick.py
mq4hemc-0.2.0.dist-info/LICENSE
mq4hemc-0.2.0.dist-info/METADATA
mq4hemc-0.2.0.dist-info/WHEEL
mq4hemc-0.2.0.dist-info/top_level.txt
mq4hemc-0.2.0.dist-info/RECORD
