Metadata-Version: 2.1
Name: mq4hemc
Version: 0.2.0
Summary: Service with Message Queue Python library
Home-page: https://github.com/oshevchenko/mq4hemc
Author: Oleksandr Shevchenko
Author-email: shevchenko.adb@gmail.com
License: MIT License
Platform: any
Classifier: Development Status :: 3 - Alpha
Classifier: Intended Audience :: Developers
Classifier: License :: OSI Approved :: MIT License
Classifier: Programming Language :: Python :: 3.8
Requires-Python: >=3.8
License-File: LICENSE
